explosig_connect/__init__.py
explosig_connect/connection.py
explosig_connect-0.0.7.dist-info/LICENSE
explosig_connect-0.0.7.dist-info/METADATA
explosig_connect-0.0.7.dist-info/WHEEL
explosig_connect-0.0.7.dist-info/top_level.txt
explosig_connect-0.0.7.dist-info/RECORD
