Metadata-Version: 2.1
Name: explosig-connect
Version: 0.0.7
Summary: Send data to ExploSig
Home-page: https://github.com/lrgr/explosig-connect
Author: Mark Keller
License: UNKNOWN
Platform: UNKNOWN
Classifier: Programming Language :: Python :: 3
Classifier: License :: OSI Approved :: MIT License
Classifier: Operating System :: OS Independent
Requires-Python: >=3.6
Requires-Dist: requests (>=2.22.0)
Requires-Dist: pandas (>=0.25.1)
